llama_cpp_python_gradio/__init__.py
llama_cpp_python_gradio-0.0.1.dist-info/METADATA
llama_cpp_python_gradio-0.0.1.dist-info/WHEEL
llama_cpp_python_gradio-0.0.1.dist-info/RECORD
