Metadata-Version: 2.3
Name: llama-cpp-python-gradio
Version: 0.0.1
Summary: A Python package for creating Gradio applications with llama.cpp models
Project-URL: homepage, https://github.com/AK391/llama-cpp-python-gradio
Project-URL: repository, https://github.com/AK391/llama-cpp-python-gradio
Author-email: AK <ahsen.khaliq@gmail.com>
Classifier: License :: OSI Approved :: MIT License
Classifier: Operating System :: OS Independent
Classifier: Programming Language :: Python :: 3
Requires-Python: >=3.10
Requires-Dist: gradio>=5.5.0
Requires-Dist: huggingface-hub
Requires-Dist: llama-cpp-python
Provides-Extra: dev
Requires-Dist: pytest; extra == 'dev'
